{
  "warnings" : [ ],
  "files" : [ "report.json", "void_EnumExample.EnumExample(EnumExample__this,_java.lang.String__name)_-581731502.json", "void_EnumExample.EnumExample(EnumExample__this,_java.lang.String__name)_-581731626.json", "void_EnumExample.EnumExample(EnumExample__this,_java.lang.String__name)_-581731750.json", "void_EnumExample.EnumExample_clinit()_1707446183.json", "void_Main.main(java.lang.String_[]__args).json" ],
  "info" : {
    "cfgs" : "4",
    "duration" : "854ms",
    "end" : "2025-09-19T12:24:31.803+02:00",
    "expressions" : "15",
    "files" : "5",
    "globals" : "20",
    "members" : "125",
    "programs" : "1",
    "start" : "2025-09-19T12:24:30.949+02:00",
    "statements" : "10",
    "units" : "41",
    "version" : "0.1",
    "warnings" : "0"
  },
  "configuration" : {
    "analysisGraphs" : "NONE",
    "descendingPhaseType" : "NONE",
    "dumpForcesUnwinding" : "false",
    "fixpointWorkingSet" : "OrderBasedWorkingSet",
    "glbThreshold" : "5",
    "hotspots" : "unset",
    "jsonOutput" : "true",
    "openCallPolicy" : "ReturnTopPolicy",
    "optimize" : "false",
    "recursionWideningThreshold" : "5",
    "semanticChecks" : "",
    "serializeInputs" : "false",
    "serializeResults" : "true",
    "shouldSmashError" : "unset",
    "syntacticChecks" : "",
    "useWideningPoints" : "true",
    "wideningThreshold" : "5",
    "workdir" : "java-outputs/enum/enum01"
  }
}